{
  "category_3": {
    "id": 3,
    "data": [{
      "appName": "途家-短租民宿",
      "company": "途家网网络技术（北京）有限公司",
      "phone": "400-188-1234"
    }, {
      "appName": "货拉拉司机版",
      "company": "货拉拉",
      "phone": "10103636"
    }, {
      "appName": "同程旅游-酒店机票",
      "company": "同程网络科技股份有限公司",
      "phone": "400-777-7777"
    }, {
      "appName": "首旅如家",
      "company": "如家酒店集团",
      "phone": "10103333"
    }, {
      "appName": "维也纳酒店",
      "company": "维也纳酒店有限公司",
      "phone": "400-888-2888"
    }, {
      "appName": "奥凯航空",
      "company": "奥凯航空有限公司",
      "phone": "95307"
    }, {
      "appName": "飞猪-订火车票机票",
      "company": "淘宝（中国）软件有限公司",
      "phone": "9510208"
    }, {
      "appName": "欧尚评驾",
      "company": "上海评驾科技有限公司",
      "phone": "400-101-2211"
    }, {
      "appName": "曹操专车",
      "company": "杭州优行科技有限公司",
      "phone": "400-608-1111"
    }, {
      "appName": "金立差旅",
      "company": "517旅行网",
      "phone": "400-779-6666"
    }, {
      "appName": "世界邦行程大师",
      "company": "世界邦（北京）信息技术有限公司",
      "phone": "400-664-6888"
    }, {
      "appName": "艺龙旅行-酒店机票",
      "company": "艺龙网信息技术（北京）有限公司",
      "phone": "400-933-3333"
    }, {
      "appName": "Agoda",
      "company": "Agoda",
      "phone": "400-636-6838"
    }, {
      "appName": "华凌物流干线司机",
      "company": "新疆华凌物流配送有限公司",
      "phone": "400-889-9800"
    }, {
      "appName": "腾讯地图",
      "company": "腾讯科技（深圳）有限公司",
      "phone": "0755-83765566"
    }, {
      "appName": "飞常准",
      "company": "合肥飞友网络科技有限公司",
      "phone": "400-635-0787"
    }, {
      "appName": "时行别克校园版",
      "company": "上汽通用汽车有限公司",
      "phone": "400-820-2020"
    }, {
      "appName": "会小二",
      "company": "北京云动数字媒体技术有限公司",
      "phone": "400-991-2828"
    }, {
      "appName": "吉祥航空",
      "company": "上海吉祥航空股份有限公司",
      "phone": "021-95520"
    }, {
      "appName": "驴妈妈旅游",
      "company": "上海景域文化传播股份有限公司",
      "phone": "1010-6060"
    }, {
      "appName": "车享家",
      "company": "上海赛可电子商务有限公司",
      "phone": "400-802-0666"
    }, {
      "appName": "欧拉车享",
      "company": "纷时科技",
      "phone": "400-802-0666"
    }, {
      "appName": "车车车险",
      "company": "北京车与车科技有限公司",
      "phone": "400-015-0999"
    }, {
      "appName": "智行火车票12306高铁抢票",
      "company": "上海迅途票务代理有限公司",
      "phone": "12306"
    }, {
      "appName": "香港航空",
      "company": "香港航空有限公司",
      "phone": "950715"
    }, {
      "appName": "铁友火车票12306高铁抢票",
      "company": "上海迅途票务代理有限公司",
      "phone": "12306"
    }, {
      "appName": "华凌物流干线货主",
      "company": "新疆华凌物流配送有限公司",
      "phone": "400-889-9800"
    }, {
      "appName": "春秋航空",
      "company": "春秋航空",
      "phone": "95524"
    }, {
      "appName": "滴滴车主",
      "company": "滴滴出行科技有限公司",
      "phone": "400-000-0999"
    }, {
      "appName": "同程商旅",
      "company": "同程商旅",
      "phone": "400-777-7777"
    }, {
      "appName": "百度地图",
      "company": "北京百度网讯科技有限公司",
      "phone": "400-099-8998"
    }, {
      "appName": "大众出行",
      "company": "上海大众出行信息技术股份有限公司",
      "phone": "400-188-0888"
    }, {
      "appName": "蚂蚁短租-民宿预订",
      "company": "北京裕山阳科技发展有限公司",
      "phone": "400-028-6868"
    }, {
      "appName": "租租车",
      "company": "广州力挚网络科技有限公司",
      "phone": "1010-1020"
    }, {
      "appName": "去哪儿旅行",
      "company": "上海赫程国际旅行社有限公司",
      "phone": "95117"
    }, {
      "appName": "货拉拉企业版",
      "company": "货拉拉",
      "phone": "10103636"
    }, {
      "appName": "宝骏新能源",
      "company": "上汽通用五菱汽车股份有限公司",
      "phone": "400-861-2345"
    }, {
      "appName": "环球黑卡",
      "company": "谛听网络技术（杭州）有限公司",
      "phone": "400-080-1616"
    }, {
      "appName": "粤通卡",
      "company": "广东联合电子服务股份有限公司",
      "phone": "96533"
    }, {
      "appName": "摩拜单车",
      "company": "北京摩拜科技有限公司",
      "phone": "400-811-7799"
    }, {
      "appName": "携程企业商旅",
      "company": "携程旅游网络技术（上海）有限公司",
      "phone": "95010"
    }, {
      "appName": "惠租车-海外自驾旅游租车平台",
      "company": "上海途顺网络科技有限公司",
      "phone": "400-188-8820"
    }, {
      "appName": "滴滴企业版",
      "company": "北京小桔科技有限公司",
      "phone": "400-000-0999"
    }, {
      "appName": "中国人保",
      "company": "中国人民财产保险股份有限公司",
      "phone": "95518"
    }, {
      "appName": "Booking.com",
      "company": "Booking.com",
      "phone": "400-882-2810"
    }, {
      "appName": "乌镇旅游",
      "company": "中景艺（北京）旅游文化有限公司",
      "phone": "0573-88731088"
    }, {
      "appName": "优信拍",
      "company": "优信互联（北京）信息技术有限公司",
      "phone": "101-010-88"
    }, {
      "appName": "地上铁",
      "company": "地上铁租车（深圳）有限公司",
      "phone": "400-860-4558"
    }, {
      "appName": "陆风智联",
      "company": "南昌陆风汽车营销有限公司",
      "phone": "400-883-3666"
    }, {
      "appName": "易游移动助手",
      "company": "易全退",
      "phone": "10086"
    }, {
      "appName": "去哪儿机票",
      "company": "北京趣拿信息技术有限公司",
      "phone": "95117"
    }, {
      "appName": "GoFun出行",
      "company": "北京首汽智行科技有限公司",
      "phone": "400-019-0808"
    }, {
      "appName": "高铁管家12306火车票",
      "company": "深圳市活力天汇科技股份有限公司",
      "phone": "12306"
    }, {
      "appName": "58估车价",
      "company": "北京五八信息技术有限公司",
      "phone": "10105858"
    }, {
      "appName": "巴士管家",
      "company": "车巴达（苏州）网络科技有限公司",
      "phone": "400-100-0456"
    }, {
      "appName": "首都航空",
      "company": "首都航空",
      "phone": "95375"
    }, {
      "appName": "神州专车",
      "company": "神州优车（福建）信息技术有限公司",
      "phone": "400-616-6666"
    }, {
      "appName": "南湖国旅严选",
      "company": "广州南湖粤途国际旅行社有限公司",
      "phone": "400-084-0008"
    }, {
      "appName": "途牛旅游-机票酒店",
      "company": "南京途牛科技有限公司",
      "phone": "400-799-9999"
    }, {
      "appName": "南方航空",
      "company": "中国南方航空股份有限公司",
      "phone": "400-669-5539"
    }, {
      "appName": "首汽约车",
      "company": "首约科技（北京）有限公司",
      "phone": "10105678"
    }, {
      "appName": "春秋旅游",
      "company": "春秋旅游网",
      "phone": "400-820-6222"
    }, {
      "appName": "海南航空",
      "company": "海南航空股份有限公司",
      "phone": "95339"
    }, {
      "appName": "日产智联",
      "company": "深圳联友科技有限公司广州分公司",
      "phone": "400-830-8899"
    }, {
      "appName": "携程国际用车",
      "company": "北京唐人天下信息技术有限公司",
      "phone": "95010"
    }, {
      "appName": "中国联航",
      "company": "中国联合航空有限公司",
      "phone": "400-102-6666"
    }, {
      "appName": "美团打车",
      "company": "上海路团科技有限公司",
      "phone": "10107888"
    }, {
      "appName": "一嗨租车",
      "company": "上海一嗨汽车租赁有限公司",
      "phone": "400-888-6608"
    }, {
      "appName": "北京一卡通",
      "company": "北京市政交通一卡通有限公司",
      "phone": "010-96066"
    }, {
      "appName": "福特派",
      "company": "福特汽车(中国)有限公司",
      "phone": "400-887-7766"
    }, {
      "appName": "酒店哥哥",
      "company": "上海会甲信息技术有限公司",
      "phone": "400-821-3148"
    }, {
      "appName": "滴滴出行",
      "company": "北京小桔科技有限公司",
      "phone": "400-000-0999"
    }, {
      "appName": "优步-Uber",
      "company": "上海雾博信息技术有限公司",
      "phone": "400-000-6555"
    }, {
      "appName": "平安快轿",
      "company": "北京平安快轿科技有限公司",
      "phone": "95511"
    }, {
      "appName": "深圳航空",
      "company": "深圳航空有限责任公司",
      "phone": "95361"
    }, {
      "appName": "神行太保",
      "company": "上海微漂信息技术有限公司",
      "phone": "95500"
    }, {
      "appName": "保汇通",
      "company": "保汇通（厦门）网络科技有限公司",
      "phone": "95320"
    }, {
      "appName": "瑞卡租车",
      "company": "广州瑞致租车有限公司",
      "phone": "400-777-0888"
    }, {
      "appName": "康辉旅游",
      "company": "康辉旅游网",
      "phone": "400-019-8198"
    }, {
      "appName": "START-原PP租车",
      "company": "爱车汇（北京）科技有限责任公司",
      "phone": "400-999-9666"
    }, {
      "appName": "N-BOOKING",
      "company": "南京途牛科技有限公司",
      "phone": "400-882-2810"
    }, {
      "appName": "听游天下",
      "company": "北京安平时空网络科技有限公司",
      "phone": "400-630-0088"
    }, {
      "appName": "TDS移动端",
      "company": "重庆海外旅业集团有限公司",
      "phone": "10086"
    }, {
      "appName": "白山掌上公交",
      "company": "白山市公共交通有限公司",
      "phone": "0592-5128197"
    }, {
      "appName": "驾图车小秘",
      "company": "驾图信科技有限公司",
      "phone": "400-025-7787"
    }],
    "count": 85
  }
}