{
  "category_1": {
    "id": 1,
    "data": [{
      "appName": "CiCi",
      "company": "联动卓越（北京）网络科技有限公司",
      "phone": "010-88934365",
      "mail": "ldjoy@ldjoy.com"
    }, {
      "appName": "喵来了",
      "company": "多玩游戏网",
      "phone": "020-82120116",
      "mail": "hudun@yy.com"
    }, {
      "appName": "空耳",
      "company": "上海移云信息科技有限公司",
      "phone": "021-31001181",
      "mail": "1cloud@1cloud.cn"
    }, {
      "appName": "加马语聊",
      "company": "杭州加马行乐科技有限公司",
      "phone": "15921420950",
      "mail": "baja@daoke.me"
    }, {
      "appName": "CiCi",
      "company": "联动卓越（北京）网络科技有限公司",
      "phone": "010-88934365",
      "mail": "ldjoy@ldjoy.com"
    }, {
      "appName": "喵来了",
      "company": "多玩游戏网",
      "phone": "020-82120116",
      "mail": "hudun@yy.com"
    }, {
      "appName": "陪我聊",
      "company": "广州巅玥信息科技有限公司",
      "phone": "020-85279624",
      "mail": "chenge@hongyanapp.com"
    }, {
      "appName": "百度 Hi",
      "company": "百度在线网络技术（北京）有限公司",
      "phone": "010-59928888",
      "mail": "service-center@baidu.com"
    }, {
      "appName": "渔获",
      "company": "索罗特信息科技江苏有限公司",
      "phone": "0510-66888275",
      "mail": "zhoulinyan@solot.com"
    }, {
      "appName": "兔聊-一对一视频",
      "company": "深圳市镜玩科技有限公司",
      "phone": "0755-36604892",
      "mail": "155157394@qq.com"
    }, {
      "appName": "聚会玩",
      "company": "上海梦六网络科技有限公司",
      "phone": "13918098841",
      "mail": null
    }, {
      "appName": "荣威车友会",
      "company": "Li Tang",
      "phone": "0760-23116839",
      "mail": null
    }, {
      "appName": "新玻人脉",
      "company": "佛山市页外软件科技有限公司",
      "phone": "13687421613",
      "mail": null
    }, {
      "appName": "名表圈",
      "company": "匡匡匡",
      "phone": "18762607379",
      "mail": "2269647879@qq.com"
    }, {
      "appName": "配配-高颜值cp陪玩社区",
      "company": "深圳齐享娱乐科技有限公司",
      "phone": "17377957200",
      "mail": "1654134@qq.com"
    }, {
      "appName": "口袋小安",
      "company": "安徽安大笃北信息科技有限责任公司",
      "phone": "15655198315",
      "mail": "congorz@yeah.net"
    }, {
      "appName": "CiliCili-电竞资讯app",
      "company": "深圳市驰基电竞互娱有限公司",
      "phone": "15707901503",
      "mail": "pengwei@cj99.com"
    }, {
      "appName": "印象",
      "company": "广州美人信息技术有限公司",
      "phone": "18501645715",
      "mail": "info@adnonstop.com"
    }, {
      "appName": "一加一",
      "company": "深圳市南迦网络科技有限公司",
      "phone": "13691703375",
      "mail": "2355607464@qq.com"
    }, {
      "appName": "大邯郸",
      "company": "河北牛团电子商务有限公司",
      "phone": "13315099986",
      "mail": "172239925@qq.com"
    }, {
      "appName": "空耳",
      "company": "上海移云信息科技有限公司",
      "phone": "021-31001181",
      "mail": "1cloud@1cloud.cn"
    }, {
      "appName": "加马语聊",
      "company": "杭州加马行乐科技有限公司",
      "phone": "15921420950",
      "mail": "baja@daoke.me"
    }, {
      "appName": "CiCi",
      "company": "联动卓越（北京）网络科技有限公司",
      "phone": "010-88934365",
      "mail": "ldjoy@ldjoy.com"
    }, {
      "appName": "喵来了",
      "company": "多玩游戏网",
      "phone": "020-82120116",
      "mail": "hudun@yy.com"
    }, {
      "appName": "陪我聊",
      "company": "广州巅玥信息科技有限公司",
      "phone": "020-85279624",
      "mail": "chenge@hongyanapp.com"
    }, {
      "appName": "百度 Hi",
      "company": "百度在线网络技术（北京）有限公司",
      "phone": "010-59928888",
      "mail": "service-center@baidu.com"
    }, {
      "appName": "渔获",
      "company": "索罗特信息科技江苏有限公司",
      "phone": "0510-66888275",
      "mail": "zhoulinyan@solot.com"
    }, {
      "appName": "兔聊-一对一视频",
      "company": "深圳市镜玩科技有限公司",
      "phone": "0755-36604892",
      "mail": "155157394@qq.com"
    }, {
      "appName": "聚会玩",
      "company": "上海梦六网络科技有限公司",
      "phone": "13918098841",
      "mail": null
    }, {
      "appName": "荣威车友会",
      "company": "Li Tang",
      "phone": "0760-23116839",
      "mail": null
    }, {
      "appName": "新玻人脉",
      "company": "佛山市页外软件科技有限公司",
      "phone": "13687421613",
      "mail": null
    }, {
      "appName": "医生圈",
      "company": "深圳市大辰科技有限公司",
      "phone": "15814585524",
      "mail": "zhangmp@dachentech.com.cn"
    }, {
      "appName": "小米社区",
      "company": "小米科技",
      "phone": "60606666-1000",
      "mail": "chenchongwei@xiaomi.com"
    }, {
      "appName": "捏他",
      "company": "ACGneta",
      "phone": null,
      "mail": "pay@tongbu.com"
    }, {
      "appName": "越野侠",
      "company": "杭州侠客行户外活动策划有限公司",
      "phone": "0571-89806391",
      "mail": null
    }, {
      "appName": "正中会",
      "company": "深圳左邻永佳科技有限公司",
      "phone": "0755-82131809",
      "mail": "admin@zuolin.com"
    }, {
      "appName": "红人直播",
      "company": "北京微联通技术有限公司",
      "phone": "010-56013581",
      "mail": "shuang.ding@hongle.tv"
    }, {
      "appName": "Tinkle",
      "company": "宝瓶汇",
      "phone": "15626260940",
      "mail": "412576349@qq.com"
    }, {
      "appName": "NewFace新脸孔",
      "company": "ChenYiQing",
      "phone": "15880224426",
      "mail": null
    }, {
      "appName": "首席信才",
      "company": "青岛联创天下人力资源服务有限公司",
      "phone": "18366273343",
      "mail": "569433228@qq.com"
    }, {
      "appName": "奇集",
      "company": "中山市尊一互动广告有限公司",
      "phone": "0760-88889658",
      "mail": "yinghuan.he@zun1.com"
    }, {
      "appName": "1107社区",
      "company": "黑龙江省熙然软件开发有限公司",
      "phone": "18145156888",
      "mail": "18145156888@163.com"
    }, {
      "appName": "约电影",
      "company": "厦门市定向网媒资讯有限公司",
      "phone": "18106083392",
      "mail": null
    }, {
      "appName": "一游说",
      "company": "广州初放信息技术有限公司",
      "phone": "020-38061161",
      "mail": "liulimei@xingfeiinc.com"
    }, {
      "appName": "去敲敲",
      "company": "杭州头名科技有限公司",
      "phone": "18658193211",
      "mail": null
    }, {
      "appName": "知乎极速版",
      "company": "智者四海（北京）技术有限公司",
      "phone": "61190680",
      "mail": "finance@zhihu.com"
    }, {
      "appName": "AQ",
      "company": "广州中瀛信息科技有限公司",
      "phone": "18520288283",
      "mail": "740377645@qq.com"
    }, {
      "appName": "567代理",
      "company": "资生金网络科技有限公司",
      "phone": "18011347881",
      "mail": null
    }, {
      "appName": "FashIcon",
      "company": "FashIcon",
      "phone": "13302128623",
      "mail": "315582467@qq.com"
    }, {
      "appName": "唔哩星球",
      "company": "咕唧科技",
      "phone": "18257131476",
      "mail": null
    }, {
      "appName": "传声筒",
      "company": "志融信联（北京）科技有限公司",
      "phone": "010-82872650",
      "mail": null
    }, {
      "appName": "概率论",
      "company": "上海见寻文化创意有限公司",
      "phone": "13585718047",
      "mail": "qinyuyingyouli@foxmail.com"
    }, {
      "appName": "情侣玩吧-交友约会",
      "company": "洋曼科（深圳）科技有限公司",
      "phone": "13603018996",
      "mail": "289078007@qq.com"
    }, {
      "appName": "Gorkor",
      "company": "深圳市桃源纪科技有限公司",
      "phone": "13600409529",
      "mail": "360113636@qq.com"
    }, {
      "appName": "小天才",
      "company": "广东小天才科技有限公司",
      "phone": "0769-85540888",
      "mail": "tgj888@gdbbk.com"
    }, {
      "appName": "星商汇园区",
      "company": "深圳左邻永佳科技有限公司",
      "phone": "0755-82131809",
      "mail": "admin@zuolin.com"
    }, {
      "appName": "心聊",
      "company": "爆米花（杭州）科技有限公司",
      "phone": "89936135",
      "mail": "admin@baomihua.com"
    }, {
      "appName": "爱保山",
      "company": "云南千树信息技术有限公司",
      "phone": "18669074241",
      "mail": null
    }, {
      "appName": "小红书",
      "company": "行吟信息科技(上海)有限公司",
      "phone": "13761762237",
      "mail": "qli4@xiaohongshu.com"
    }, {
      "appName": "一约-聊天交友",
      "company": "广州九伴信息科技有限公司",
      "phone": "15011991869",
      "mail": "15011991869@163.com"
    }, {
      "appName": "SegmentFault",
      "company": "SegmentFault",
      "phone": "13866626312",
      "mail": null
    }, {
      "appName": "豆瓣",
      "company": "北京豆瓣互动科技有限公司",
      "phone": "010-58478561",
      "mail": "fengyongfang@douban.com"
    }, {
      "appName": "面对面",
      "company": "面对面科技股份有限公司",
      "phone": "0769-87527979",
      "mail": null
    }, {
      "appName": "番薯小组",
      "company": "北京尽欢科技有限公司",
      "phone": "010-83030229",
      "mail": "zhongsen@bigo.sg"
    }, {
      "appName": "精脉客源",
      "company": "搜教网络科技（上海）有限公司",
      "phone": "021-54500106",
      "mail": "170493994@qq.com"
    }, {
      "appName": "知己交友",
      "company": "海口知己网络科技股份有限公司",
      "phone": "0898-68591697",
      "mail": "2363443469@qq.com"
    }, {
      "appName": "Hello大叔",
      "company": "北京星河时代信息技术有限公司",
      "phone": "13651286826",
      "mail": "yuchunyou@myhug.cn"
    }, {
      "appName": "斗图表情包",
      "company": "武汉网幂科技有限公司",
      "phone": "87610250",
      "mail": "li.yuan@lafonapps.com"
    }, {
      "appName": "7天情侣处cp",
      "company": "杭州五次颜网络科技有限公司",
      "phone": "18069867520",
      "mail": null
    }, {
      "appName": "花镇情感-恋爱情侣",
      "company": "广州花镇教育咨询有限公司",
      "phone": "020-81133889",
      "mail": "hzhr@huazhen.com"
    }, {
      "appName": "草莓聊-聊天交友",
      "company": "深圳燃冰信息科技有限公司",
      "phone": "15821953258",
      "mail": "1477852625@qq.com"
    }, {
      "appName": "吹牛",
      "company": "北京青曙网络科技有限公司",
      "phone": "010-53512029",
      "mail": "web@meetqs.com"
    }, {
      "appName": "王者人生",
      "company": "深圳市腾讯计算机系统有限公司",
      "phone": "0755-86013388",
      "mail": "landyzhang@tencent.com"
    }, {
      "appName": "",
      "company": "",
      "phone": "010-68085031",
      "mail": "jgry1029@adbc.com.cn"
    }, {
      "appName": "",
      "company": "",
      "phone": "010-68085031",
      "mail": "jgry1029@adbc.com.cn"
    }, {
      "appName": "",
      "company": "",
      "phone": "010-68085031",
      "mail": "jgry1029@adbc.com.cn"
    }, {
      "appName": "",
      "company": "",
      "phone": "010-68085031",
      "mail": "jgry1029@adbc.com.cn"
    }, {
      "appName": "",
      "company": "",
      "phone": "010-68085031",
      "mail": "jgry1029@adbc.com.cn"
    }, {
      "appName": "",
      "company": "",
      "phone": "010-68085031",
      "mail": "jgry1029@adbc.com.cn"
    }, {
      "appName": "",
      "company": "",
      "phone": "010-68085031",
      "mail": "jgry1029@adbc.com.cn"
    }, {
      "appName": "",
      "company": "",
      "phone": "010-68085031",
      "mail": "jgry1029@adbc.com.cn"
    }],
    "count": 81
  }
}